retrieve_schedule.py
setup.py
primaverasound_2013.egg-info/PKG-INFO
primaverasound_2013.egg-info/SOURCES.txt
primaverasound_2013.egg-info/dependency_links.txt
primaverasound_2013.egg-info/requires.txt
primaverasound_2013.egg-info/top_level.txt
scraper/__init__.py
scraper/primaverasound/__init__.py
scraper/primaverasound/schedule.py