Metadata-Version: 1.1
Name: primaverasound-2013
Version: 00.00.90
Summary: Primavera Sound 2013 Schedule scraper per day and Concert for http://primaverasound.com
Home-page: http://ricardogarfe.github.com/primaverasound/
Author: Ricardo García Fernández
Author-email: ricardogarfe@gmail.com
License: Apache v2.0
Download-URL: https://github.com/ricardogarfe/primaverasound/archive/master.zip
Keywords: primaverasound
Platform: UNKNOWN
